[
	{
		"Data": "milknew",
		"Neighbor": 5,
		"Min_support": 9,
		"FSM": [
			[
				1035,
				1036
			],
			[
				1013,
				1021
			],
			[
				988,
				998,
				1000
			],
			[
				962,
				970
			],
			[
				954,
				963
			],
			[
				936,
				940
			],
			[
				920,
				924
			],
			[
				914,
				918
			],
			[
				891,
				897,
				904
			],
			[
				880,
				888
			],
			[
				871,
				873
			],
			[
				846,
				857,
				864
			],
			[
				833,
				841
			],
			[
				819,
				827
			],
			[
				811,
				820
			],
			[
				782,
				786
			],
			[
				767,
				775
			],
			[
				763,
				773
			],
			[
				747,
				756
			],
			[
				740,
				748
			],
			[
				744,
				745
			],
			[
				733,
				741
			],
			[
				728,
				735
			],
			[
				726,
				731
			],
			[
				711,
				718
			],
			[
				708,
				715
			],
			[
				677,
				685
			],
			[
				669,
				673
			],
			[
				655,
				662
			],
			[
				634,
				642
			],
			[
				621,
				628
			],
			[
				614,
				623
			],
			[
				610,
				612
			],
			[
				591,
				601
			],
			[
				597,
				599
			],
			[
				590,
				595
			],
			[
				575,
				584,
				593
			],
			[
				577,
				586
			],
			[
				570,
				579
			],
			[
				555,
				561
			],
			[
				542,
				549
			],
			[
				538,
				545
			],
			[
				535,
				544
			],
			[
				532,
				531,
				533
			],
			[
				512,
				522
			],
			[
				518,
				520
			],
			[
				511,
				516
			],
			[
				505,
				514
			],
			[
				488,
				496
			],
			[
				482,
				490
			],
			[
				476,
				483
			],
			[
				474,
				481
			],
			[
				468,
				477
			],
			[
				441,
				442
			],
			[
				425,
				434
			],
			[
				374,
				381
			],
			[
				364,
				373
			],
			[
				343,
				351
			],
			[
				335,
				339
			],
			[
				320,
				328
			],
			[
				317,
				324
			],
			[
				311,
				313
			],
			[
				300,
				309
			],
			[
				293,
				301
			],
			[
				261,
				269
			],
			[
				260,
				268
			],
			[
				255,
				263
			],
			[
				236,
				245
			],
			[
				215,
				223
			],
			[
				207,
				211
			],
			[
				192,
				200
			],
			[
				172,
				181
			],
			[
				174,
				175
			],
			[
				165,
				173
			],
			[
				169,
				170
			],
			[
				149,
				158
			],
			[
				155,
				157
			],
			[
				148,
				153
			],
			[
				142,
				151
			],
			[
				125,
				133
			],
			[
				119,
				127
			],
			[
				113,
				120
			],
			[
				111,
				118
			],
			[
				105,
				114
			],
			[
				86,
				95
			],
			[
				60,
				68
			],
			[
				42,
				39,
				43
			],
			[
				33,
				41
			],
			[
				36,
				40
			],
			[
				14,
				22
			],
			[
				7,
				1,
				11
			]
		]
	},
	{
		"Data": "milknew",
		"Neighbor": 5,
		"Min_support": 8,
		"FSM": [
			[
				1035,
				1036
			],
			[
				1013,
				1021
			],
			[
				996,
				1003
			],
			[
				988,
				998,
				1000
			],
			[
				962,
				970
			],
			[
				954,
				963
			],
			[
				935,
				943
			],
			[
				920,
				924
			],
			[
				906,
				912
			],
			[
				880,
				886
			],
			[
				867,
				874
			],
			[
				833,
				841
			],
			[
				819,
				827
			],
			[
				811,
				820
			],
			[
				801,
				806
			],
			[
				782,
				786
			],
			[
				767,
				775
			],
			[
				763,
				773
			],
			[
				747,
				756
			],
			[
				740,
				748
			],
			[
				744,
				745
			],
			[
				733,
				741
			],
			[
				728,
				735
			],
			[
				726,
				731
			],
			[
				706,
				714,
				722
			],
			[
				711,
				718
			],
			[
				708,
				715
			],
			[
				669,
				673
			],
			[
				654,
				666
			],
			[
				655,
				662
			],
			[
				634,
				640
			],
			[
				621,
				628
			],
			[
				614,
				623
			],
			[
				610,
				612
			],
			[
				591,
				601
			],
			[
				597,
				599
			],
			[
				590,
				595
			],
			[
				575,
				584,
				593
			],
			[
				577,
				586
			],
			[
				570,
				579
			],
			[
				555,
				561
			],
			[
				542,
				549
			],
			[
				538,
				545
			],
			[
				535,
				544
			],
			[
				532,
				531,
				533
			],
			[
				512,
				522
			],
			[
				518,
				520
			],
			[
				511,
				516
			],
			[
				505,
				514
			],
			[
				488,
				496
			],
			[
				482,
				490
			],
			[
				476,
				483
			],
			[
				474,
				481
			],
			[
				468,
				477
			],
			[
				441,
				442
			],
			[
				425,
				434
			],
			[
				419,
				431
			],
			[
				399,
				410
			],
			[
				374,
				381
			],
			[
				364,
				373
			],
			[
				343,
				351
			],
			[
				335,
				339
			],
			[
				320,
				328
			],
			[
				317,
				324
			],
			[
				311,
				313
			],
			[
				300,
				309
			],
			[
				293,
				301
			],
			[
				261,
				269
			],
			[
				260,
				268
			],
			[
				255,
				263
			],
			[
				236,
				245
			],
			[
				215,
				223
			],
			[
				207,
				211
			],
			[
				192,
				200
			],
			[
				172,
				181
			],
			[
				174,
				175
			],
			[
				165,
				173
			],
			[
				169,
				170
			],
			[
				149,
				158
			],
			[
				155,
				157
			],
			[
				148,
				153
			],
			[
				142,
				151
			],
			[
				125,
				133
			],
			[
				119,
				127
			],
			[
				113,
				120
			],
			[
				111,
				118
			],
			[
				105,
				114
			],
			[
				86,
				95
			],
			[
				60,
				68
			],
			[
				42,
				39,
				43
			],
			[
				33,
				41
			],
			[
				36,
				40
			],
			[
				20,
				31
			],
			[
				14,
				22
			]
		]
	},
	{
		"Data": "milknew",
		"Neighbor": 5,
		"Min_support": 7,
		"FSM": [
			[
				1035,
				1036
			],
			[
				1013,
				1021
			],
			[
				1006,
				1018
			],
			[
				996,
				1003
			],
			[
				988,
				998,
				1000
			],
			[
				962,
				970
			],
			[
				954,
				963
			],
			[
				935,
				943
			],
			[
				936,
				940
			],
			[
				920,
				924
			],
			[
				914,
				918
			],
			[
				906,
				912
			],
			[
				880,
				886
			],
			[
				867,
				874
			],
			[
				850,
				859
			],
			[
				840,
				844,
				851
			],
			[
				833,
				841
			],
			[
				811,
				820
			],
			[
				790,
				798
			],
			[
				782,
				786
			],
			[
				767,
				775
			],
			[
				747,
				756
			],
			[
				740,
				748
			],
			[
				744,
				745
			],
			[
				733,
				741
			],
			[
				728,
				735
			],
			[
				726,
				731
			],
			[
				706,
				714,
				722
			],
			[
				711,
				718
			],
			[
				708,
				715
			],
			[
				669,
				673
			],
			[
				654,
				666
			],
			[
				655,
				662
			],
			[
				659,
				660
			],
			[
				634,
				640
			],
			[
				621,
				628
			],
			[
				614,
				623
			],
			[
				611,
				610,
				612
			],
			[
				591,
				601
			],
			[
				597,
				599
			],
			[
				590,
				595
			],
			[
				575,
				584,
				593
			],
			[
				577,
				586
			],
			[
				570,
				579
			],
			[
				555,
				561
			],
			[
				542,
				549
			],
			[
				538,
				545
			],
			[
				535,
				544
			],
			[
				532,
				531,
				533
			],
			[
				512,
				522
			],
			[
				518,
				520
			],
			[
				511,
				516
			],
			[
				505,
				514
			],
			[
				488,
				496
			],
			[
				482,
				490
			],
			[
				476,
				483
			],
			[
				474,
				481
			],
			[
				468,
				477
			],
			[
				441,
				442
			],
			[
				425,
				434
			],
			[
				419,
				431
			],
			[
				399,
				410
			],
			[
				374,
				381
			],
			[
				364,
				373
			],
			[
				343,
				351
			],
			[
				335,
				339
			],
			[
				320,
				328
			],
			[
				317,
				324
			],
			[
				311,
				313
			],
			[
				300,
				309
			],
			[
				293,
				301
			],
			[
				261,
				269
			],
			[
				260,
				268
			],
			[
				255,
				263
			],
			[
				236,
				245
			],
			[
				215,
				223
			],
			[
				207,
				211
			],
			[
				192,
				200
			],
			[
				172,
				181
			],
			[
				171,
				180
			],
			[
				174,
				175
			],
			[
				165,
				173
			],
			[
				169,
				170
			],
			[
				149,
				158
			],
			[
				142,
				151
			],
			[
				125,
				133
			],
			[
				119,
				127
			],
			[
				113,
				120
			],
			[
				99,
				111,
				118
			],
			[
				105,
				114
			],
			[
				86,
				95
			],
			[
				85,
				94
			],
			[
				79,
				90
			],
			[
				88,
				89
			],
			[
				57,
				64
			],
			[
				51,
				53
			],
			[
				36,
				40
			],
			[
				32,
				39
			],
			[
				20,
				31
			]
		]
	},
	{
		"Data": "milknew",
		"Neighbor": 5,
		"Min_support": 6,
		"FSM": [
			[
				1035,
				1036
			],
			[
				1013,
				1021
			],
			[
				1006,
				1018
			],
			[
				996,
				1003
			],
			[
				988,
				998,
				1000
			],
			[
				964,
				978
			],
			[
				962,
				970
			],
			[
				954,
				963
			],
			[
				935,
				943
			],
			[
				936,
				940
			],
			[
				929,
				938
			],
			[
				914,
				918
			],
			[
				906,
				912
			],
			[
				885,
				890
			],
			[
				880,
				886
			],
			[
				867,
				874
			],
			[
				850,
				859
			],
			[
				840,
				844,
				851
			],
			[
				833,
				841
			],
			[
				811,
				820
			],
			[
				790,
				798
			],
			[
				782,
				786
			],
			[
				770,
				777,
				783
			],
			[
				767,
				775
			],
			[
				747,
				756
			],
			[
				740,
				748
			],
			[
				744,
				745
			],
			[
				733,
				741
			],
			[
				720,
				728,
				735
			],
			[
				726,
				731
			],
			[
				706,
				714,
				722
			],
			[
				708,
				715
			],
			[
				688,
				693
			],
			[
				669,
				673
			],
			[
				664,
				670
			],
			[
				654,
				666
			],
			[
				655,
				662
			],
			[
				647,
				649
			],
			[
				639,
				644
			],
			[
				634,
				640
			],
			[
				621,
				628
			],
			[
				614,
				623
			],
			[
				607,
				615
			],
			[
				611,
				612
			],
			[
				591,
				601
			],
			[
				597,
				599
			],
			[
				590,
				595
			],
			[
				575,
				584,
				593
			],
			[
				570,
				579
			],
			[
				555,
				561
			],
			[
				542,
				549
			],
			[
				538,
				545
			],
			[
				535,
				544
			],
			[
				532,
				531,
				533
			],
			[
				512,
				522
			],
			[
				518,
				520
			],
			[
				502,
				511,
				516
			],
			[
				505,
				514
			],
			[
				491,
				498
			],
			[
				488,
				496
			],
			[
				463,
				467
			],
			[
				457,
				459
			],
			[
				425,
				434
			],
			[
				419,
				431
			],
			[
				403,
				412
			],
			[
				374,
				381
			],
			[
				364,
				373
			],
			[
				346,
				353
			],
			[
				343,
				351
			],
			[
				335,
				339,
				349
			],
			[
				323,
				330,
				334
			],
			[
				320,
				328
			],
			[
				317,
				324
			],
			[
				311,
				313
			],
			[
				300,
				309
			],
			[
				299,
				308
			],
			[
				293,
				301
			],
			[
				274,
				284
			],
			[
				261,
				269
			],
			[
				260,
				268
			],
			[
				257,
				258
			],
			[
				236,
				245
			],
			[
				215,
				223
			],
			[
				207,
				211
			],
			[
				195,
				202,
				208
			],
			[
				192,
				200
			],
			[
				172,
				181
			],
			[
				171,
				175
			],
			[
				165,
				173
			],
			[
				169,
				170
			],
			[
				149,
				158
			],
			[
				142,
				151
			],
			[
				139,
				148
			],
			[
				125,
				133
			],
			[
				113,
				120
			],
			[
				105,
				114
			],
			[
				99,
				111
			],
			[
				85,
				94
			],
			[
				83,
				92
			],
			[
				79,
				90
			],
			[
				88,
				89
			],
			[
				57,
				64
			],
			[
				51,
				53
			],
			[
				37,
				40
			],
			[
				32,
				39
			],
			[
				20,
				31
			],
			[
				14,
				22
			]
		]
	}
]